tkshapes/__init__.py
tkshapes/gcanvas.py
tkshapes/gconnection.py
tkshapes/gevent.py
tkshapes/gitem.py
tkshapes/gnode.py
tkshapes/gobject.py
tkshapes/gobjects/__init__.py
tkshapes/gobjects/gandgate.py
tkshapes/gobjects/gbuffergate.py
tkshapes/gobjects/ggraphpaper.py
tkshapes/gobjects/glightbulb.py
tkshapes/gobjects/gnandgate.py
tkshapes/gobjects/gnorgate.py
tkshapes/gobjects/gnotgate.py
tkshapes/gobjects/gorgate.py
tkshapes/gobjects/goval.py
tkshapes/gobjects/gpolygon.py
tkshapes/gobjects/gpythonlogo.py
tkshapes/gobjects/grect.py
tkshapes/gobjects/gswitch.py
tkshapes/gobjects/gwire.py
tkshapes/gobjects/gxnorgate.py
tkshapes/gobjects/gxorgate.py
tkshapes-0.0.4.dist-info/LICENSE
tkshapes-0.0.4.dist-info/METADATA
tkshapes-0.0.4.dist-info/WHEEL
tkshapes-0.0.4.dist-info/top_level.txt
tkshapes-0.0.4.dist-info/RECORD
