Metadata-Version: 2.1
Name: tkshapes
Version: 0.0.4
Summary: Draw and interact with shapes on the Tkinter canvas
Home-page: https://github.com/bentlema/tkshapes
Author: Mark Bentley
Author-email: bentlema@yahoo.com
License: UNKNOWN
Project-URL: Bug Reports, https://github.com/bentlema/tkshapes/issues
Project-URL: Source, https://github.com/bentlema/tkshapes/
Keywords: tkinter
Platform: UNKNOWN
Classifier: Development Status :: 3 - Alpha
Classifier: Intended Audience :: Developers
Classifier: License :: OSI Approved :: GNU General Public License v3 (GPLv3)
Classifier: Programming Language :: Python :: 3.6
Classifier: Programming Language :: Python :: 3.7
